setup.py
OSolntseva_server.egg-info/PKG-INFO
OSolntseva_server.egg-info/SOURCES.txt
OSolntseva_server.egg-info/dependency_links.txt
OSolntseva_server.egg-info/requires.txt
OSolntseva_server.egg-info/top_level.txt
server/__init__.py
server/my_server.py
server/logs/__init__.py
server/logs/client_log_config.py
server/logs/server_log_config.py
server/logs/configs/__init__.py
server/logs/configs/client_log_config.py
server/logs/configs/server_log_config.py
server/server/__init__.py
server/server/add_user.py
server/server/config_window.py
server/server/core.py
server/server/delete_user.py
server/server/main_window.py
server/server/serv_database.py
server/server/statistic_window.py